telegram_cli/__init__.py
telegram_cli/__main__.py
telegram_cli/cli.py
telegram_cli/telegram.py
telegram_cli-0.3.0.dist-info/LICENSE
telegram_cli-0.3.0.dist-info/METADATA
telegram_cli-0.3.0.dist-info/WHEEL
telegram_cli-0.3.0.dist-info/entry_points.txt
telegram_cli-0.3.0.dist-info/top_level.txt
telegram_cli-0.3.0.dist-info/RECORD
