Metadata-Version: 2.1
Name: telegram-cli
Version: 0.3.0
Summary: Python CLI tool and library for sending messages to Telegram
Home-page: https://github.com/zmoog/telegram-cli
Author: Maurizio Branca
License: Apache License, Version 2.0
Project-URL: Issues, https://github.com/zmoog/telegram-cli/issues
Project-URL: CI, https://github.com/zmoog/telegram-cli/actions
Project-URL: Changelog, https://github.com/zmoog/telegram-cli/releases
Requires-Python: >=3.7
License-File: LICENSE
Requires-Dist: click
Requires-Dist: requests
Provides-Extra: test
Requires-Dist: pytest ; extra == 'test'
Requires-Dist: pytest-recording ; extra == 'test'
Requires-Dist: ruff ; extra == 'test'
